README
setup.py
pyazure/__init__.py
pyazure/hostedservices.py
pyazure/locations.py
pyazure/pyazure.py
pyazure/storageaccounts.py
pyazure/util.py
pyazure.egg-info/PKG-INFO
pyazure.egg-info/SOURCES.txt
pyazure.egg-info/dependency_links.txt
pyazure.egg-info/top_level.txt
pyazure/storage/__init__.py
pyazure/storage/blob.py
pyazure/storage/django_storage.py
pyazure/storage/queue.py
pyazure/storage/table.py